odoo8_addon_account_easy_reconcile-8.0.1.3.1.99.dev98-py3.8-nspkg.pth
odoo_addons/account_easy_reconcile/README.rst
odoo_addons/account_easy_reconcile/__init__.py
odoo_addons/account_easy_reconcile/__openerp__.py
odoo_addons/account_easy_reconcile/base_reconciliation.py
odoo_addons/account_easy_reconcile/easy_reconcile.py
odoo_addons/account_easy_reconcile/easy_reconcile.xml
odoo_addons/account_easy_reconcile/easy_reconcile_history.py
odoo_addons/account_easy_reconcile/easy_reconcile_history_view.xml
odoo_addons/account_easy_reconcile/res_config.py
odoo_addons/account_easy_reconcile/res_config_view.xml
odoo_addons/account_easy_reconcile/simple_reconciliation.py
odoo_addons/account_easy_reconcile/i18n/account_easy_reconcile.pot
odoo_addons/account_easy_reconcile/i18n/am.po
odoo_addons/account_easy_reconcile/i18n/ar.po
odoo_addons/account_easy_reconcile/i18n/bg.po
odoo_addons/account_easy_reconcile/i18n/bs.po
odoo_addons/account_easy_reconcile/i18n/ca.po
odoo_addons/account_easy_reconcile/i18n/ca_ES.po
odoo_addons/account_easy_reconcile/i18n/cs.po
odoo_addons/account_easy_reconcile/i18n/da.po
odoo_addons/account_easy_reconcile/i18n/da_DK.po
odoo_addons/account_easy_reconcile/i18n/de.po
odoo_addons/account_easy_reconcile/i18n/el_GR.po
odoo_addons/account_easy_reconcile/i18n/en_GB.po
odoo_addons/account_easy_reconcile/i18n/es.po
odoo_addons/account_easy_reconcile/i18n/es_AR.po
odoo_addons/account_easy_reconcile/i18n/es_CL.po
odoo_addons/account_easy_reconcile/i18n/es_CO.po
odoo_addons/account_easy_reconcile/i18n/es_CR.po
odoo_addons/account_easy_reconcile/i18n/es_DO.po
odoo_addons/account_easy_reconcile/i18n/es_EC.po
odoo_addons/account_easy_reconcile/i18n/es_ES.po
odoo_addons/account_easy_reconcile/i18n/es_MX.po
odoo_addons/account_easy_reconcile/i18n/es_PE.po
odoo_addons/account_easy_reconcile/i18n/es_PY.po
odoo_addons/account_easy_reconcile/i18n/es_VE.po
odoo_addons/account_easy_reconcile/i18n/et.po
odoo_addons/account_easy_reconcile/i18n/fa.po
odoo8_addon_account_easy_reconcile-8.0.1.3.1.99.dev98.dist-info/METADATA
odoo8_addon_account_easy_reconcile-8.0.1.3.1.99.dev98.dist-info/WHEEL
odoo8_addon_account_easy_reconcile-8.0.1.3.1.99.dev98.dist-info/namespace_packages.txt
odoo8_addon_account_easy_reconcile-8.0.1.3.1.99.dev98.dist-info/top_level.txt
odoo8_addon_account_easy_reconcile-8.0.1.3.1.99.dev98.dist-info/RECORD
